MANIFEST.in
README.rst
setup.py
Cola.egg-info/PKG-INFO
Cola.egg-info/SOURCES.txt
Cola.egg-info/dependency_links.txt
Cola.egg-info/entry_points.txt
Cola.egg-info/requires.txt
Cola.egg-info/top_level.txt
app/__init__.py
app/weibo/__init__.py
app/weibo/bundle.py
app/weibo/conf.py
app/weibo/login.py
app/weibo/parsers.py
app/weibo/storage.py
app/weibo/utils.py
app/wiki/__init__.py
cola/__init__.py
cola/cmdline.py
cola/context.py
cola/settings.py
cola/cluster/__init__.py
cola/cluster/master.py
cola/cluster/stage.py
cola/cluster/tracker.py
cola/cluster/worker.py
cola/commands/__init__.py
cola/commands/job.py
cola/commands/master.py
cola/commands/startproject.py
cola/commands/worker.py
cola/conf/main.yaml
cola/core/__init__.py
cola/core/config.py
cola/core/counter.py
cola/core/dedup.py
cola/core/errors.py
cola/core/handlers.py
cola/core/logs.py
cola/core/opener.py
cola/core/parsers.py
cola/core/rpc.py
cola/core/unit.py
cola/core/urls.py
cola/core/utils.py
cola/core/zip.py
cola/core/bloomfilter/__init__.py
cola/core/bloomfilter/hashtype.py
cola/core/extractor/__init__.py
cola/core/extractor/preprocess.py
cola/core/extractor/readability.py
cola/core/extractor/utils.py
cola/core/mq/__init__.py
cola/core/mq/client.py
cola/core/mq/distributor.py
cola/core/mq/hash_ring.py
cola/core/mq/node.py
cola/core/mq/store.py
cola/core/mq/utils.py
cola/functions/__init__.py
cola/functions/budget.py
cola/functions/counter.py
cola/functions/speed.py
cola/job/__init__.py
cola/job/container.py
cola/job/executor.py
cola/job/task.py